centralized_rate_limiter/__init__.py
centralized_rate_limiter/rate_limiting.py
centralized_rate_limiter-0.1.11.dist-info/LICENSE
centralized_rate_limiter-0.1.11.dist-info/METADATA
centralized_rate_limiter-0.1.11.dist-info/WHEEL
centralized_rate_limiter-0.1.11.dist-info/top_level.txt
centralized_rate_limiter-0.1.11.dist-info/RECORD
