Metadata-Version: 2.1
Name: centralized-rate-limiter
Version: 0.1.11
Summary: Utility for handling rate limiting in a centralized manner
Author-email: Jacopo Piccirillo <jacopo.piccirillo@gmail.com>
Project-URL: Homepage, https://github.com/waddafunk/CentralizedRateLimiter
Project-URL: Bug Tracker, https://github.com/waddafunk/CentralizedRateLimiter/issues
Project-URL: Documentation, https://github.com/waddafunk/CentralizedRateLimiter#readme
Classifier: Programming Language :: Python :: 3
Classifier: License :: OSI Approved :: Apache Software License
Classifier: Operating System :: OS Independent
Classifier: Development Status :: 4 - Beta
Classifier: Intended Audience :: Developers
Classifier: Topic :: Software Development :: Libraries :: Python Modules
Classifier: Topic :: Internet :: WWW/HTTP
Requires-Python: >=3.7
License-File: LICENSE
Requires-Dist: requests >=2.25.0
Requires-Dist: ratelimit >=2.2.1
Provides-Extra: dev
Requires-Dist: pytest >=7.0 ; extra == 'dev'
Requires-Dist: pytest-cov >=4.0 ; extra == 'dev'
Requires-Dist: responses >=0.23.0 ; extra == 'dev'
Requires-Dist: black >=22.0 ; extra == 'dev'
Requires-Dist: isort >=5.0 ; extra == 'dev'
Requires-Dist: pylint >=2.17.0 ; extra == 'dev'
Requires-Dist: pyupgrade >=3.3.0 ; extra == 'dev'
Requires-Dist: build >=0.10.0 ; extra == 'dev'
Requires-Dist: twine >=4.0.0 ; extra == 'dev'
